simpl/__init__.py
simpl/admin.py
simpl/apps.py
simpl/auth0.py
simpl/constants.py
simpl/managers.py
simpl/models.py
simpl/nav.py
simpl/receivers.py
simpl/urls.py
simpl/views.py
simpl/conf/__init__.py
simpl/conf/app_settings.py
simpl/migrations/0001_initial.py
simpl/migrations/0002_run_data.py
simpl/migrations/0003_auto_20210701_1047.py
simpl/migrations/0004_rename_token_apitoken.py
simpl/migrations/0005_auto_20210707_0934.py
simpl/migrations/0005_auto_20210712_0038.py
simpl/migrations/0006_auto_20210712_0240.py
simpl/migrations/0007_shorten_lobby_name.py
simpl/migrations/0008_merge_20210727_1117.py
simpl/migrations/0009_player_inactive.py
simpl/migrations/0010_class.py
simpl/migrations/0011_gameexperience_experience_id.py
simpl/migrations/0012_remove_lobby_ready.py
simpl/migrations/0013_gameexperience_multiplayer.py
simpl/migrations/0014_auto_20210903_1514.py
simpl/migrations/0015_lobby_instance.py
simpl/migrations/0016_link_lobby_instances.py
simpl/migrations/0017_run_date_continuous_end.py
simpl/migrations/0018_apitoken_name.py
simpl/migrations/0019_auto_20211027_1812.py
simpl/migrations/0020_auto_20211109_2056.py
simpl/migrations/__init__.py
simpl/schema/__init__.py
simpl/schema/mutations.py
simpl/schema/query.py
simpl/schema/types.py
simpl/schema/external/__init__.py
simpl/schema/external/auth0.py
simpl/schema/external/mutations.py
simpl/schema/external/query.py
simpl/schema/external/types.py
simpl/schema/external/utils.py
simpl/static/simpl/simpl.es.js
simpl/static/simpl/simpl.umd.js
simpl/static/simpl/style.css
simpl/templates/simpl/base.html
simpl/templates/simpl/run_config.html
simpl/templates/simpl/run_debrief.html
simpl/templates/simpl/run_end_gameplay.html
simpl/templates/simpl/run_players.html
simpl/templates/simpl/run_prepare.html
simpl/templates/simpl/run_start.html
simpl/templates/simpl/run_status.html
simpl/templates/simpl/run_team.html
simpl/templates/simpl/includes/dropdown-item.html
simpl/templates/simpl/includes/dropdown.html
simpl_cloud-1.3.0.dist-info/LICENSE
simpl_cloud-1.3.0.dist-info/METADATA
simpl_cloud-1.3.0.dist-info/WHEEL
simpl_cloud-1.3.0.dist-info/top_level.txt
simpl_cloud-1.3.0.dist-info/RECORD
