Metadata-Version: 2.1
Name: simpl-cloud
Version: 1.3.0
Summary: Base models and API for Django-based simulations.
Home-page: https://github.com/Wharton-Interactive/simpl-cloud
Author: Chris Beaven
Author-email: smileychris@gmail.com
License: GPL2
Keywords: api simulation administration
Platform: UNKNOWN
Classifier: Development Status :: 3 - Alpha
Classifier: Environment :: Web Environment
Classifier: Intended Audience :: Developers
Classifier: License :: OSI Approved :: GNU General Public License v2 (GPLv2)
Classifier: Operating System :: OS Independent
Classifier: Programming Language :: Python
Classifier: Programming Language :: Python :: 3 :: Only
Classifier: Programming Language :: Python :: 3.7
Classifier: Programming Language :: Python :: 3.8
Classifier: Programming Language :: Python :: 3.9
Classifier: Framework :: Django
Classifier: Framework :: Django :: 2.2
Classifier: Framework :: Django :: 3.0
Classifier: Framework :: Django :: 3.1
Classifier: Framework :: Django :: 3.2
License-File: LICENSE
Requires-Dist: Faker
Requires-Dist: mmh3
Requires-Dist: murmurhash3
Requires-Dist: graphene-django (<3)
Requires-Dist: django-allauth
Requires-Dist: packaging (<21)
Provides-Extra: api
Requires-Dist: auth0-python (<4) ; extra == 'api'
Provides-Extra: dev
Requires-Dist: tox ; extra == 'dev'
Requires-Dist: black ; extra == 'dev'
Requires-Dist: django ; extra == 'dev'
Requires-Dist: pytest ; extra == 'dev'
Requires-Dist: pytest-django ; extra == 'dev'
Provides-Extra: maintainer
Requires-Dist: zest.releaser[recommended] ; extra == 'maintainer'
Provides-Extra: test
Requires-Dist: pytest ; extra == 'test'
Requires-Dist: pytest-django ; extra == 'test'
Requires-Dist: pytest-cov ; extra == 'test'
Requires-Dist: model-bakery ; extra == 'test'
Requires-Dist: auth0-python (<4) ; extra == 'test'
Requires-Dist: psycopg2-binary ; extra == 'test'
